LICENSE.txt
MANIFEST.in
README.md
VERSION
pyproject.toml
setup.cfg
setup.py
nordigen_ha_lib.egg-info/PKG-INFO
nordigen_ha_lib.egg-info/SOURCES.txt
nordigen_ha_lib.egg-info/dependency_links.txt
nordigen_ha_lib.egg-info/not-zip-safe
nordigen_ha_lib.egg-info/requires.txt
nordigen_ha_lib.egg-info/top_level.txt
nordigen_lib/__init__.py
nordigen_lib/sensor.py