Metadata-Version: 2.1
Name: nordigen-ha-lib
Version: 0.1.6
Summary: Home Assistant lib for integration with Nordigen banking API's using nordigen-python
Home-page: https://github.com/dogmatic69/nordigen-ha-lib
Author: Carl Sutton (dogmatic69)
Author-email: dogmatic69@gmail.com
License: MIT
Keywords: nordigen,banking,home hassistant,hassio
Platform: UNKNOWN
Classifier: Development Status :: 3 - Alpha
Classifier: Programming Language :: Python :: 3.8
Classifier: License :: OSI Approved :: MIT License
Classifier: Operating System :: OS Independent
Classifier: Intended Audience :: Developers
Requires-Python: >=3.6
Provides-Extra: production
Provides-Extra: test
Provides-Extra: lint
Provides-Extra: docs
Provides-Extra: dev
Provides-Extra: deploy
